<annotation verified="yes"><folder>images</folder><filename>6638f63b3b6b43ec97943c4e308f60d3__1.jpg</filename><path>D:\EveryFuckingProgram_home\tf_train\images\6638f63b3b6b43ec97943c4e308f60d3__1.jpg</path><source><database>Faradenza_DB</database></source><size><width>564</width><height>716</height><depth>3</depth></size><segmented>0</segmented><object><name>hand</name><pose>Unspecified</pose><truncated>0</truncated><difficult>0</difficult><bndbox><xmin>382</xmin><ymin>220</ymin><xmax>448</xmax><ymax>311</ymax></bndbox></object></annotation>